{
    "초반 빌드업 요약": [
        "다리우스",
        "드레이븐",
        "바이올렛",
        "파우더",
        "밴더"
    ],
    "[상징] 6자동기계 코그모": [
        "아무무",
        "녹턴",
        "누누와 윌럼프",
        "블리츠크랭크",
        "코그모",
        "문도 박사",
        "트위치",
        "말자하"
    ],
    "4자동기계 4기타대 녹턴": [
        "아무무",
        "녹턴",
        "아칼리",
        "블리츠크랭크",
        "코그모",
        "트위스티드 페이트",
        "암베사",
        "케이틀린"
    ],
    "3가족 6투사 바이올렛": [
        "다리우스",
        "드레이븐",
        "바이올렛",
        "파우더",
        "밴더",
        "우르곳",
        "갱플랭크",
        "바이",
        "세비카"
    ],
    "6감시자 코르키 딩거": [
        "이렐리아",
        "레오나",
        "렐",
        "로리스",
        "이즈리얼",
        "일라오이",
        "코르키",
        "하이머딩거",
        "럼블"
    ],
    "[상징] 7반군 징크스": [
        "세트",
        "아칼리",
        "이즈리얼",
        "에코",
        "일라오이",
        "조이",
        "럼블",
        "징크스"
    ],
    "5장미단 4지배자 실코": [
        "모르가나",
        "블라디미르",
        "카시오페아",
        "가렌",
        "문도 박사",
        "실코",
        "엘리스",
        "르블랑",
        "모데카이저"
    ],
    "집행자 바이 케이틀린": [
        "매디",
        "카밀",
        "로리스",
        "트위스티드 페이트",
        "바이",
        "에코",
        "럼블",
        "세비카",
        "케이틀린"
    ],
    "[상징] 6난동꾼 트위치": [
        "스텝",
        "세트",
        "누누와 윌럼프",
        "레니",
        "문도 박사",
        "엘리스",
        "트위치",
        "케이틀린"
    ],
    "5실험체 트위치": [
        "자이라",
        "우르곳",
        "누누와 윌럼프",
        "문도 박사",
        "바이",
        "엘리스",
        "트위치",
        "모데카이저",
        "케이틀린"
    ],
    "4사절 암베사 코르키": [
        "트리스타나",
        "갱플랭크",
        "나미",
        "스웨인",
        "트위스티드 페이트",
        "가렌",
        "바이",
        "암베사",
        "코르키"
    ],
    "6고물상 코르키": [
        "트런들",
        "파우더",
        "갱플랭크",
        "에코",
        "엘리스",
        "일라오이",
        "코르키",
        "럼블"
    ],
    "4감시자 4선도자 레나타": [
        "모르가나",
        "벡스",
        "신지드",
        "이렐리아",
        "레나타 글라스크",
        "레오나",
        "렐"
    ],
    "4감시자 4포수 트타": [
        "이렐리아",
        "레오나",
        "렐",
        "우르곳",
        "트리스타나",
        "이즈리얼",
        "일라오이",
        "코르키"
    ],
    "4사절 4포수 트리스타나": [
        "렐",
        "우르곳",
        "트리스타나",
        "나미",
        "이즈리얼",
        "가렌",
        "암베사",
        "코르키"
    ],
    "4형태전환자 갱플랭크": [
        "렐",
        "갱플랭크",
        "나미",
        "누누와 윌럼프",
        "스웨인",
        "바이",
        "엘리스",
        "제이스"
    ],
    "6화공 남작 실코": [
        "신지드",
        "레나타 글라스크",
        "우르곳",
        "누누와 윌럼프",
        "레니",
        "스미치",
        "문도 박사",
        "실코",
        "세비카"
    ],
    "4사절 4마법사 나미": [
        "블라디미르",
        "트리스타나",
        "나미",
        "스웨인",
        "가렌",
        "암베사",
        "엘리스",
        "르블랑"
    ],
    "6주시자 코그모": [
        "다리우스",
        "아무무",
        "밴더",
        "블라디미르",
        "제리",
        "스카",
        "코그모",
        "가렌"
    ],
    "5장미단 4선도자 딩거": [
        "모르가나",
        "블라디미르",
        "누누와 윌럼프",
        "카시오페아",
        "가렌",
        "엘리스",
        "하이머딩거",
        "르블랑",
        "말자하"
    ],
    "6정복자 모데카이저": [
        "다리우스",
        "드레이븐",
        "렐",
        "갱플랭크",
        "스웨인",
        "바이",
        "암베사",
        "모데카이저",
        "세비카"
    ],
    "[상징] 8선도자 딩거": [
        "모르가나",
        "벡스",
        "레나타 글라스크",
        "렐",
        "누누와 윌럼프",
        "엘리스",
        "하이머딩거",
        "말자하"
    ],
    "[영원한 브론즈] 팀 구성": [
        "렐",
        "우르곳",
        "트리스타나",
        "문도 박사",
        "바이",
        "트위치",
        "럼블",
        "모데카이저",
        "케이틀린"
    ],
    "[상징] 8마법사 르블랑": [
        "럭스",
        "자이라",
        "블라디미르",
        "나미",
        "스웨인",
        "엘리스",
        "조이",
        "르블랑"
    ],
    "[힘을 향한 갈망] 우르곳": [
        "드레이븐",
        "자이라",
        "세트",
        "우르곳",
        "트리스타나",
        "갱플랭크",
        "누누와 윌럼프",
        "바이"
    ],
    "[특성 추적자] 활성화": [
        "자이라",
        "렐",
        "우르곳",
        "트리스타나",
        "갱플랭크",
        "누누와 윌럼프",
        "스웨인"
    ]
}